AlgoM/__init__.py
AlgoM/Geometry/__init__.py
AlgoM/Graph/__init__.py
AlgoM/Query/__init__.py
AlgoM/Structure/__init__.py
AlgoM/Tree/__init__.py
AlgoM-1.4.dist-info/LICENSE
AlgoM-1.4.dist-info/METADATA
AlgoM-1.4.dist-info/WHEEL
AlgoM-1.4.dist-info/top_level.txt
AlgoM-1.4.dist-info/RECORD
