Metadata-Version: 2.1
Name: AlgoM
Version: 1.4
Summary: Python algorithms and data structures library
Home-page: https://github.com/martarel/AlgoPack
Author: Marta Religa
Author-email: marta.religa@hotmail.com
License: UNKNOWN
Platform: UNKNOWN
Classifier: Programming Language :: Python :: 3
Classifier: License :: OSI Approved :: MIT License
Classifier: Operating System :: OS Independent
Requires-Python: >=3.6
License-File: LICENSE
